{
    "homepage": "https://github.com/ffftp/ffftp",
    "version": "4.7",
    "license": "BSD 3-clause",
    "architecture": {
        "64bit": {
            "url": "https://github.com/ffftp/ffftp/releases/download/v4.7/ffftp-v4.7-x64.zip",
            "hash": "8df692f643628b234b78696d239dd451235a359f9bbcba01c6df2c856580612f"
        },
        "32bit": {
            "url": "https://github.com/ffftp/ffftp/releases/download/v4.7/ffftp-v4.7-x86.zip",
            "hash": "a37a47b47a6d8fec46e112d4b11c79edfbd71b5f6bb1f9adffd5ea8ee2083d0d"
        }
    },
    "pre_install": [
        "if (-not (Test-Path \"$persist_dir\\ffftp.ini\")) { New-Item \"$dir\\ffftp.ini\" | Out-Null }"
    ],
    "persist": "ffftp.ini",
    "shortcuts": [
        [
            "FFFTP.exe",
            "FFFTP"
        ]
    ],
    "checkver": "github",
    "autoupdate": {
        "architecture": {
            "64bit": {
                "url": "https://github.com/ffftp/ffftp/releases/download/v$version/ffftp-v$version-x64.zip"
            },
            "32bit": {
                "url": "https://github.com/ffftp/ffftp/releases/download/v$version/ffftp-v$version-x86.zip"
            }
        }
    }
}
